README
setup.py
moodle/__init__.py
moodle/moodle.py
moodle.egg-info/PKG-INFO
moodle.egg-info/SOURCES.txt
moodle.egg-info/dependency_links.txt
moodle.egg-info/not-zip-safe
moodle.egg-info/top_level.txt