Metadata-Version: 1.1
Name: moodle
Version: 0.0.1
Summary: Moodle web services connection library
Home-page: UNKNOWN
Author: Zikzakmedia SL
Author-email: zikzak@zikzakmedia.com
License: GNU Affero General Public License v3
Platform: any
Classifier: Development Status :: 4 - Beta
Classifier: Environment :: Web Environment
Classifier: Intended Audience :: Developers
Classifier: License :: OSI Approved :: GNU Affero General Public License v3
Classifier: Operating System :: OS Independent
Classifier: Programming Language :: Python
Classifier: Topic :: Internet :: WWW/HTTP :: Dynamic Content
Classifier: Topic :: Software Development :: Libraries :: Python Modules
